dophon_properties/__init__.py
dophon_properties/cloud/__init__.py
dophon_properties/cloud/client/__init__.py
dophon_properties/cloud/client/default_properties.py
dophon_properties/cloud/client/properties.py
dophon_properties/cloud/utils/__init__.py
dophon_properties/database/__init__.py
dophon_properties/database/default_properties.py
dophon_properties/database/properties.py
dophon_properties/dophon/__init__.py
dophon_properties/dophon/default_properties.py
dophon_properties/dophon/properties.py
dophon_properties/dophon/properties_handler.py
dophon_properties/dophon/sys_utils.py
dophon_properties/mq/__init__.py
dophon_properties/mq/default_properties.py
dophon_properties/mq/properties.py
dophon_properties/tools/__init__.py
dophon_properties-0.1.4.post7.dist-info/WHEEL
dophon_properties-0.1.4.post7.dist-info/METADATA
dophon_properties-0.1.4.post7.dist-info/RECORD
