Metadata-Version: 2.1
Name: dophon-properties
Version: 0.1.4.post7
Summary: dophon properties module
Keywords: web,framework,dophon
Author: CallMeE
Author-email: ealohu@163.com
Requires-Python: >=3.6,<4.0
Classifier: Programming Language :: Python :: 3
Classifier: Programming Language :: Python :: 3.6
Classifier: Programming Language :: Python :: 3.7
Classifier: Programming Language :: Python :: 3.8
Requires-Dist: PyYAML
